{"cameraMode":{"drawMode":0,"name":"Shaded","section":"Shading Mode"},"sceneLighting":false,"audioPlay":false,"sceneViewState":{"showFog":true,"showMaterialUpdate":false,"showSkybox":false,"showFlares":true,"showImageEffects":true,"showParticleSystems":true},"in2DMode":false,"pivot":{"x":-0.000004351139068603516,"y":-0.17540407180786134,"z":0.04901940003037453},"rotation":{"x":0.08728428930044174,"y":-0.88443523645401,"z":0.1838023066520691,"w":0.42008379101753237},"size":2.325329542160034,"orthographic":false}